userkit/__init__.py
userkit/email.py
userkit/emails.py
userkit/error.py
userkit/invite.py
userkit/invites.py
userkit/log.py
userkit/logs.py
userkit/requestor.py
userkit/session.py
userkit/user.py
userkit/users.py
userkit/widget.py
userkit-1.0.0.dist-info/LICENSE
userkit-1.0.0.dist-info/METADATA
userkit-1.0.0.dist-info/WHEEL
userkit-1.0.0.dist-info/top_level.txt
userkit-1.0.0.dist-info/RECORD
