Metadata-Version: 2.1
Name: userkit
Version: 1.0.0
Summary: Python bindings for UserKit: user login and account management
Home-page: https://github.com/workpail/userkit-python
Author: Workpail
Author-email: info@workpail.com
License: MIT
Platform: UNKNOWN
Classifier: License :: OSI Approved :: MIT License
Classifier: Programming Language :: Python :: 3
Classifier: Programming Language :: Python :: 3.7
Requires-Dist: requests
